{
"type": "FeatureCollection",
"crs": { "type": "name", "properties": { "name": "urn:ogc:def:crs:OGC:1.3:CRS84" } },
                                                                                
"features": [
{ "type": "Feature", "properties": { "ProjectRet": null, "YearRetire": null, "Comments": null, "Status": "Active", "Consequenc": 0.000000, "Probabilit": 0.000000, "Mitigation": 0.000000, "Risk": 0.000000, "EstimatedL": 0, "Installati": null, "Replacemen": 0.000000, "CostingDat": null, "Asset_ID": "SSTP0000001" }, "geometry": { "type": "Point", "coordinates": [ -96.787003101368001, 46.924388189456259 ] } }
]
}
